Metadata-Version: 2.1
Name: kivy-garden.ebs.clocks
Version: 1.0.1
Summary: Clock widgets for Kivy
Home-page: https://github.com/ebs-universe/kivy_garden.ebs.clocks
Author: Chintalagiri Shashank
Author-email: shashank.chintalagiri@gmail.com
License: UNKNOWN
Project-URL: Bug Reports, https://github.com/ebs-universe/kivy_garden.ebs.clocks/issues
Project-URL: Source, https://github.com/ebs-universe/kivy_garden.ebs.clocks
Keywords: Kivy kivy-garden
Platform: UNKNOWN
Classifier: Development Status :: 4 - Beta
Classifier: Intended Audience :: Developers
Classifier: Topic :: Software Development :: Libraries
Classifier: License :: OSI Approved :: MIT License
Classifier: Programming Language :: Python :: 3.5
Classifier: Programming Language :: Python :: 3.6
Classifier: Programming Language :: Python :: 3.7
Classifier: Programming Language :: Python :: 3.8
Classifier: Programming Language :: Python :: 3.9
Classifier: Programming Language :: Python :: 3.10
Provides-Extra: dev
Provides-Extra: ci
